exonum_instance_configuration_plugin/__init__.py
exonum_instance_configuration_plugin/plugin.py
exonum_instance_configuration_plugin/proto/exonum/java/service_pb2.py
exonum_java_runtime_plugin/__init__.py
exonum_java_runtime_plugin/plugin.py
exonum_java_runtime_plugin/proto/exonum/java/deploy_arguments_pb2.py
exonum_launcher_java_plugins-0.10.0.dist-info/LICENSE
exonum_launcher_java_plugins-0.10.0.dist-info/METADATA
exonum_launcher_java_plugins-0.10.0.dist-info/WHEEL
exonum_launcher_java_plugins-0.10.0.dist-info/top_level.txt
exonum_launcher_java_plugins-0.10.0.dist-info/RECORD
