Metadata-Version: 2.1
Name: exonum-launcher-java-plugins
Version: 0.10.0
Summary: Exonum Java plugins for exonum-launcher
Home-page: https://github.com/exonum/exonum-java-binding
Author: The Exonum team
Author-email: contact@exonum.com
License: UNKNOWN
Platform: UNKNOWN
Classifier: Programming Language :: Python :: 3
Classifier: License :: OSI Approved :: Apache Software License
Classifier: Operating System :: OS Independent
Classifier: Topic :: Security :: Cryptography
Requires-Python: >=3.6
Requires-Dist: exonum-launcher (==0.2.0)
